Metadata-Version: 2.1
Name: hawksoft.ptaScore
Version: 1.0.1
Summary: 针对pintia.cn网站教学，生成学生的多次作业成绩总表。
Home-page: https://gitee.com/xingyongkang/ptaScore
Author: xingyongkang
Author-email: xingyongkang@cqu.edu.cn
License: MIT
Keywords: pintia,excel
Platform: any
